{
  "procedure": {
    "id": "5.3.13",
    "title": "RRC connection resume",
    "slug": "5.3.13-rrc-connection-resume"
  },
  "transition_coverage": [
    {
      "id": "5.3.13-transition-1",
      "steps": [
        1
      ],
      "states": [
        "RRC_INACTIVE",
        "RRC_RESUME_REQUESTED"
      ]
    },
    {
      "id": "5.3.13-transition-2",
      "steps": [
        2
      ],
      "states": [
        "RRC_RESUME_REQUESTED",
        "RRC_CONNECTED"
      ]
    },
    {
      "id": "5.3.13-transition-3",
      "steps": [
        3
      ],
      "states": [
        "RRC_RESUME_REQUESTED",
        "RRC_CONNECTED"
      ]
    },
    {
      "id": "5.3.13-transition-4",
      "steps": [
        4
      ],
      "states": [
        "RRC_RESUME_REQUESTED",
        "RRC_IDLE"
      ]
    },
    {
      "id": "5.3.13-transition-5",
      "steps": [
        5
      ],
      "states": [
        "RRC_RESUME_REQUESTED",
        "RRC_IDLE"
      ]
    }
  ],
  "two_switch_paths": [
    {
      "id": "5.3.13-path-1-2",
      "steps": [
        1,
        2
      ],
      "states": [
        "RRC_INACTIVE",
        "RRC_RESUME_REQUESTED",
        "RRC_CONNECTED"
      ]
    },
    {
      "id": "5.3.13-path-1-3",
      "steps": [
        1,
        3
      ],
      "states": [
        "RRC_INACTIVE",
        "RRC_RESUME_REQUESTED",
        "RRC_CONNECTED"
      ]
    },
    {
      "id": "5.3.13-path-1-4",
      "steps": [
        1,
        4
      ],
      "states": [
        "RRC_INACTIVE",
        "RRC_RESUME_REQUESTED",
        "RRC_IDLE"
      ]
    },
    {
      "id": "5.3.13-path-1-5",
      "steps": [
        1,
        5
      ],
      "states": [
        "RRC_INACTIVE",
        "RRC_RESUME_REQUESTED",
        "RRC_IDLE"
      ]
    }
  ]
}
